README.md
license.txt
setup.cfg
setup.py
cordsearch/__init__.py
cordsearch.egg-info/PKG-INFO
cordsearch.egg-info/SOURCES.txt
cordsearch.egg-info/dependency_links.txt
cordsearch.egg-info/requires.txt
cordsearch.egg-info/top_level.txt
cordsearch/core/__init__.py
cordsearch/core/cord_dataset.py
cordsearch/tests/__init__.py
cordsearch/tests/test_cord_dataset.py