Metadata-Version: 2.1
Name: cordsearch
Version: 0.2.1
Summary: Utility package for computing and finding similar sentences in passages
Home-page: https://github.com/IanBluth/cordsearch
Classifier: Programming Language :: Python :: 3
Classifier: License :: OSI Approved :: Apache Software License
Classifier: Operating System :: OS Independent
Classifier: Topic :: Scientific/Engineering :: Artificial Intelligence
License-File: license.txt
